web3_checksum/__init__.py
web3_checksum/get_checksum_address.py
zk_modules-0.1.1.dist-info/LICENSE.txt
zk_modules-0.1.1.dist-info/METADATA
zk_modules-0.1.1.dist-info/WHEEL
zk_modules-0.1.1.dist-info/top_level.txt
zk_modules-0.1.1.dist-info/RECORD
